{
	"instance" : {
		"allPlayersPositions" : "sebastian 10/1/2017 19:12",
		"createdBy" : "AgusTossi 9/19/2017 20:51",
		"keepingTrackOfPlayerIndex" : "sebastian 10/1/2017 17:13",
		"dice" : "sebastian 9/9/2017 19:30",
		"nextTurn:" : "SebastianCalderone 11/2/2017 14:54",
		"winnerOfTheGame" : "sebastian 10/1/2017 17:14",
		"numberOfPlayers" : "AgusTossi 9/19/2017 20:52",
		"position:" : "SebastianCalderone 10/28/2017 14:59",
		"initializeRounds:initializePlayers:initializeBoard:initializeDice:" : "SebastianCalderone 11/2/2017 15:09",
		"assertIsTheTurnof:" : "sebastian 10/1/2017 17:01",
		"positionOf:" : "sebastian 10/1/2017 17:37",
		"roundsToWin" : "sebastian 9/9/2017 19:04",
		"isWinner:" : "sebastian 10/1/2017 17:34",
		"assertGameIsNotEnded" : "AgusTossi 9/19/2017 21:32",
		"assertGameIsEnded" : "AgusTossi 9/19/2017 21:31",
		"isActive" : "AgusTossi 9/19/2017 20:59",
		"board" : "sebastian 9/9/2017 19:51",
		"state" : "sebastian 9/9/2017 19:06"
	},
	"class" : {
		"rounds:playedBy:withThisBoard:usingDice:" : "AgusTossi 9/19/2017 21:21"
	}
}